owl2yams/__init__.py
owl2yams/ccplugin.py
owl2yams/generate_appjstemplate.py
owl2yams/generate_entities.py
owl2yams/generate_init.py
owl2yams/generate_postcreate.py
owl2yams/generate_schema.py
owl2yams/generate_views.py
owl2yams/prefixes.json
owl2yams/cw_react_admin/main.js
owl2yams-1.4.0.dist-info/METADATA
owl2yams-1.4.0.dist-info/WHEEL
owl2yams-1.4.0.dist-info/entry_points.txt
owl2yams-1.4.0.dist-info/top_level.txt
owl2yams-1.4.0.dist-info/RECORD
