Metadata-Version: 2.1
Name: owl2yams
Version: 1.4.0
Summary: A tools to transforms owl into yams schema
Home-page: https://forge.extranet.logilab.fr/cubicweb/owl2yams
Author: Fabien Amarger
Author-email: famarger@logilab.fr
License: LGPL
Requires-Dist: cubicweb (<4.0.0)
Requires-Dist: yams (>=0.45.5)
Requires-Dist: rdflib
Requires-Dist: Jinja2
Requires-Dist: black
Requires-Dist: requests
Requires-Dist: redbaron
